dummy_poetry_repo/__init__.py
dummy_poetry_repo-0.1.1.dist-info/LICENSE
dummy_poetry_repo-0.1.1.dist-info/WHEEL
dummy_poetry_repo-0.1.1.dist-info/METADATA
dummy_poetry_repo-0.1.1.dist-info/RECORD
